pymssqlutils/__init__.py
pymssqlutils/databaseresult.py
pymssqlutils/helpers.py
pymssqlutils/methods.py
pymssqlutils/py.typed
pymssql_utils-0.4.2.dist-info/LICENSE
pymssql_utils-0.4.2.dist-info/WHEEL
pymssql_utils-0.4.2.dist-info/METADATA
pymssql_utils-0.4.2.dist-info/RECORD
