Metadata-Version: 2.1
Name: pymssql-utils
Version: 0.4.2
Summary: pymssql-utils is a small library that wraps pymssql to make your life easier.
Home-page: https://github.com/invokermain/pymssql-utils
License: GNU LGPLv2.1
Author: Tim OSullivan
Author-email: tim@lanster.dev
Requires-Python: >=3.7,<4.0
Classifier: License :: OSI Approved :: GNU Lesser General Public License v2 (LGPLv2)
Classifier: License :: Other/Proprietary License
Classifier: Programming Language :: Python :: 3
Classifier: Programming Language :: Python :: 3.10
Classifier: Programming Language :: Python :: 3.7
Classifier: Programming Language :: Python :: 3.8
Classifier: Programming Language :: Python :: 3.9
Classifier: Topic :: Database
Classifier: Typing :: Typed
Provides-Extra: all
Provides-Extra: json
Provides-Extra: pandas
Requires-Dist: orjson; extra == "json" or extra == "all"
Requires-Dist: pandas; extra == "pandas" or extra == "all"
Requires-Dist: pymssql (>=2.1.4,<3.0.0)
